{
  "fileName": "params-patcher.ts",
  "filePath": "packages/rpc-transport/src/params-patcher.ts",
  "url": "https://github.com/solana-labs/solana-web3.js/blob/master/packages/rpc-transport/src/params-patcher.ts",
  "summary": "The `solana-web3.js` file contains a function called `patchParamsForSolanaLabsRpc` that takes in a generic type `T` and an optional `IntegerOverflowHandler` function. The purpose of this function is to patch the parameters of a JSON RPC request to Solana Labs in order to handle integer overflow errors.\n\nThe function achieves this by recursively visiting each node in the input `params` object and checking if it is an array, object, or bigint. If it is an array or object, the function recursively calls itself on each element or property of the array/object. If it is a bigint, the function checks if it is greater than the maximum safe integer value and calls the `onIntegerOverflow` function if it is. Finally, if the node is not an array, object, or bigint, it is returned as is.\n\nThe `patchParamsForSolanaLabsRpc` function returns a patched version of the input `params` object where all bigints have been downcasted to numbers. This is done because Solana Labs does not have a data type to represent unsigned 64-bit integers (u64), so bigints must be downcasted to numbers in order to be sent in a JSON RPC request.\n\nThis function is useful in the larger `solana-web3.js` project because it allows developers to easily handle integer overflow errors when making JSON RPC requests to Solana Labs. Developers can simply call the `patchParamsForSolanaLabsRpc` function on their input parameters before sending the request, and the function will take care of downcasting any bigints and calling the `onIntegerOverflow` function if necessary.\n\nExample usage:\n\n```\nimport { patchParamsForSolanaLabsRpc } from 'solana-web3.js';\n\nconst params = {\n  amount: 10000000000000000000n, // bigint value\n  recipient: 'someSolanaAddress',\n  memo: 'Hello world'\n};\n\nconst patchedParams = patchParamsForSolanaLabsRpc(params, (keyPath, value) => {\n  console.error(`Integer overflow error at key path ${keyPath}: ${value}`);\n});\n\n// patchedParams now looks like:\n// {\n//   amount: 10000000000000000000, // number value\n//   recipient: 'someSolanaAddress',\n//   memo: 'Hello world'\n// }\n```",
  "questions": "1. What is the purpose of the `visitNode` function?\n- The `visitNode` function recursively visits each node in an object or array and applies a transformation to each node based on its type.\n\n2. Why is there a `TypescriptBug33014` type defined?\n- The `TypescriptBug33014` type is a workaround for a TypeScript bug (issue #33014) that causes type errors when using mapped types with conditional types.\n\n3. What is the purpose of the `patchParamsForSolanaLabsRpc` function?\n- The `patchParamsForSolanaLabsRpc` function takes an object or array of parameters for a Solana Labs JSON RPC request and applies a transformation to each node to handle integer overflow issues with `bigint` values."
}